copex/__init__.py
copex/checkpoint.py
copex/cli.py
copex/client.py
copex/config.py
copex/mcp.py
copex/metrics.py
copex/models.py
copex/persistence.py
copex/plan.py
copex/ralph.py
copex/tools.py
copex/ui.py
copex-0.8.5.dist-info/METADATA
copex-0.8.5.dist-info/WHEEL
copex-0.8.5.dist-info/entry_points.txt
copex-0.8.5.dist-info/licenses/LICENSE
copex-0.8.5.dist-info/RECORD
